{
	"archive" : {},
	"artifacts" : 
	[
		{
			"path" : "emulator/libemulator.a"
		}
	],
	"backtrace" : 1,
	"backtraceGraph" : 
	{
		"commands" : 
		[
			"add_library",
			"target_link_libraries",
			"target_include_directories"
		],
		"files" : 
		[
			"emulator/CMakeLists.txt"
		],
		"nodes" : 
		[
			{
				"file" : 0
			},
			{
				"command" : 0,
				"file" : 0,
				"line" : 1,
				"parent" : 0
			},
			{
				"command" : 1,
				"file" : 0,
				"line" : 7,
				"parent" : 0
			},
			{
				"command" : 2,
				"file" : 0,
				"line" : 6,
				"parent" : 0
			}
		]
	},
	"compileGroups" : 
	[
		{
			"compileCommandFragments" : 
			[
				{
					"fragment" : "-g"
				}
			],
			"includes" : 
			[
				{
					"backtrace" : 3,
					"path" : "/home/jd/gbEmu/emulator"
				},
				{
					"backtrace" : 2,
					"path" : "/home/jd/gbEmu/emulator/cpu"
				},
				{
					"backtrace" : 2,
					"path" : "/home/jd/gbEmu/emulator/cart"
				}
			],
			"language" : "C",
			"sourceIndexes" : 
			[
				0
			]
		}
	],
	"dependencies" : 
	[
		{
			"backtrace" : 2,
			"id" : "cpu::@e1af74150516db91f28d"
		},
		{
			"backtrace" : 2,
			"id" : "cart::@875e8b05de5ebae59e47"
		}
	],
	"id" : "emulator::@1c3256c8de4e75002d5e",
	"name" : "emulator",
	"nameOnDisk" : "libemulator.a",
	"paths" : 
	{
		"build" : "emulator",
		"source" : "emulator"
	},
	"sourceGroups" : 
	[
		{
			"name" : "Source Files",
			"sourceIndexes" : 
			[
				0
			]
		}
	],
	"sources" : 
	[
		{
			"backtrace" : 1,
			"compileGroupIndex" : 0,
			"path" : "emulator/emulator.c",
			"sourceGroupIndex" : 0
		}
	],
	"type" : "STATIC_LIBRARY"
}
